animeit/__init__.py
animeit/error.py
animeit/utils.py
animeit-0.0.1.dist-info/LICENSE
animeit-0.0.1.dist-info/METADATA
animeit-0.0.1.dist-info/WHEEL
animeit-0.0.1.dist-info/top_level.txt
animeit-0.0.1.dist-info/RECORD
