Metadata-Version: 2.1
Name: animeit
Version: 0.0.1
Summary: AnimeIT-API
Home-page: https://github.com/MainKronos/AnimeIT-API
Author: MainKronos
Author-email: lorenzo.chesi@live.it
License: UNKNOWN
Platform: UNKNOWN
Classifier: Programming Language :: Python :: 3
Classifier: License :: OSI Approved :: MIT License
Classifier: Operating System :: OS Independent
Requires-Python: >=3.6
Requires-Dist: requests
Requires-Dist: youtube-dl
Requires-Dist: beautifulsoup4
